vigcyph/__init__.py
vigcyph/vigenere.py
vigcyph-0.0.5.dist-info/METADATA
vigcyph-0.0.5.dist-info/WHEEL
vigcyph-0.0.5.dist-info/top_level.txt
vigcyph-0.0.5.dist-info/RECORD
