Metadata-Version: 2.1
Name: vigcyph
Version: 0.0.5
Summary: Encodes and Decodes Vigenere Cypher
Author: iguessidothings
Keywords: python,encode,decode,cypher,vigenere,code
Classifier: Intended Audience :: Developers
Classifier: Programming Language :: Python :: 3
Classifier: Operating System :: Unix
Classifier: Operating System :: MacOS :: MacOS X
Classifier: Operating System :: Microsoft :: Windows
